tsp_algorithms/__init__.py
tsp_algorithms/lib/algorithms.c
tsp_algorithms/lib/include/algorithms.h
tsp_algorithms/lib/include/metrics.h
tsp_algorithms/lib/metrics.c
tsp_algorithms/lib/tsp.c
tsp_algorithms/ctsp.pyd
tsp_algorithms/__init__.py
tsp_algorithms/lib/algorithms.c
tsp_algorithms/lib/metrics.c
tsp_algorithms/lib/tsp.c
tsp_algorithms/lib/include/algorithms.h
tsp_algorithms/lib/include/metrics.h
tsp_algorithms-0.2.0.dist-info/LICENSE.txt
tsp_algorithms-0.2.0.dist-info/WHEEL
tsp_algorithms-0.2.0.dist-info/METADATA
tsp_algorithms-0.2.0.dist-info/RECORD
