Metadata-Version: 2.1
Name: tsp-algorithms
Version: 0.2.0
Summary: TSP Algorithms developed as C extension for Python
Home-page: https://www.github.com/gustavo-sf/tsp-algorithms
License: MIT
Keywords: tsp,algorithms,c,python
Author: Gustavo-SF
Author-email: gustavo.fonseca@outlook.pt
Requires-Python: >3.7
Classifier: License :: OSI Approved :: MIT License
Classifier: Programming Language :: Python
Classifier: Programming Language :: Python :: 3
Classifier: Programming Language :: Python :: 3.8
Classifier: Programming Language :: Python :: 3.9
Classifier: Programming Language :: Python :: 3.10
Classifier: Programming Language :: Python :: 3.11
Classifier: Programming Language :: Python :: 3.10
Classifier: Programming Language :: Python :: 3.11
Classifier: Programming Language :: Python :: 3.8
Classifier: Programming Language :: Python :: 3.9
Classifier: Programming Language :: Python :: Implementation :: CPython
Project-URL: Repository, https://www.github.com/gustavo-sf/tsp-algorithms
